<?xml version="1.0" encoding="UTF-8"?>
<Tables>
  <Table name="exclusion" getall="true">
    <Inputs>
      <Attr>inputAttr1</Attr>
      <Value operation="2">OR:Test3</Value>
      <Value operation="1">OR:Test3</Value>
      <Value operation="1">X</Value>
      <Value operation="2">X</Value>
      <Value operation="2">Y</Value>
      <Value operation="1">Y</Value>
      <Value/>
      <Value/>
      <Value/>
      <Value/>
    </Inputs>
    <Outputs>
      <Attr>outputAttr1</Attr>
      <Value operation="1">not X or Y</Value>
      <Value operation="1">is X or Y</Value>
      <Value operation="1">is X</Value>
      <Value operation="1">not X</Value>
      <Value operation="1">not Y</Value>
      <Value operation="1">is Y</Value>
      <Value operation="1">fallout</Value>
      <Value/>
      <Value/>
      <Value/>
    </Outputs>
    <Status>
      <RuleStatus enabled="true"/>
      <RuleStatus enabled="true"/>
      <RuleStatus enabled="true"/>
      <RuleStatus enabled="true"/>
      <RuleStatus enabled="true"/>
      <RuleStatus enabled="true"/>
      <RuleStatus enabled="true"/>
      <RuleStatus enabled="true"/>
      <RuleStatus enabled="true"/>
      <RuleStatus enabled="true"/>
    </Status>
  </Table>
</Tables>
